Metadata-Version: 2.1
Name: truncated-binary-encoding
Version: 1.0.0
Summary: Python package implementing truncated binary encoding.
Home-page: https://github.com/LucaCappelletti94/truncated_binary_encoding
Author: Luca Cappelletti
Author-email: cappelletti.luca94@gmail.com
License: MIT
Platform: UNKNOWN
Classifier: Development Status :: 3 - Alpha
Classifier: License :: OSI Approved :: MIT License
Classifier: Programming Language :: Python :: 3
Provides-Extra: test
